utility_aws_pkg/__init__.py
utility_aws_pkg/utility_aws.py
utility_aws_pkg_chetanpatil-0.0.2.dist-info/METADATA
utility_aws_pkg_chetanpatil-0.0.2.dist-info/WHEEL
utility_aws_pkg_chetanpatil-0.0.2.dist-info/RECORD
