Metadata-Version: 2.4
Name: utility_aws_pkg_chetanpatil
Version: 0.0.2
Summary: A Python library for managing AWS services in utility management applications
Project-URL: Homepage, https://github.com/chetanpatil/utility-aws-lib
Project-URL: Bug Tracker, https://github.com/chetanpatil/utility-aws-lib/issues
Author-email: Chetan Patil <chetanpatil0050@gmail.com>
Classifier: License :: OSI Approved :: MIT License
Classifier: Operating System :: OS Independent
Classifier: Programming Language :: Python :: 3
Requires-Python: >=3.9
Requires-Dist: boto3>=1.28.0
